pystringmini/__init__.py
pystringmini/pystingmini.py
pystringmini/pystringmini.py
pystringmini/temp1.py
Pystringmini-3.1.7.dist-info/LICENSE
Pystringmini-3.1.7.dist-info/METADATA
Pystringmini-3.1.7.dist-info/WHEEL
Pystringmini-3.1.7.dist-info/dependency_links.txt
Pystringmini-3.1.7.dist-info/top_level.txt
Pystringmini-3.1.7.dist-info/RECORD
