Metadata-Version: 2.1
Name: Pystringmini
Version: 3.1.7
Summary: UNKNOWN
Home-page: https://github.com/thiyagarajan2002
Author: Thiyagarajan
Author-email: trj08012002@gmail.com
License: MIT
Platform: UNKNOWN
Classifier: Programming Language :: Python :: 3
Classifier: License :: OSI Approved :: MIT License
Classifier: Operating System :: OS Independent
Requires-Python: >=3.6
